netdrive_connector-1.3.2.data/data/share/applications/netdrive-connector.desktop
netdrive_connector-1.3.2.data/data/share/pixmaps/netdrive-connector.png
netdrive_connector-1.3.2.data/scripts/add-sftp-connector
netdrive_connector-1.3.2.data/scripts/add-webdav-connector
netdrive_connector-1.3.2.data/scripts/netdrive-connector_automountd
netdrive_connector-1.3.2.data/scripts/netdrive-connector_run-as-root
netdrive_connector-1.3.2.data/scripts/remove-sftp-connector
netdrive_connector-1.3.2.data/scripts/remove-webdav-connector
netdrive_connector-1.3.2.dist-info/DESCRIPTION.rst
netdrive_connector-1.3.2.dist-info/METADATA
netdrive_connector-1.3.2.dist-info/RECORD
netdrive_connector-1.3.2.dist-info/WHEEL
netdrive_connector-1.3.2.dist-info/entry_points.txt
netdrive_connector-1.3.2.dist-info/metadata.json
netdrive_connector-1.3.2.dist-info/top_level.txt
netdriveconnector/LoginDialog.py
netdriveconnector/LoginDialog.ui
netdriveconnector/NetdriveConnector.py
netdriveconnector/NetdriveConnector.ui
netdriveconnector/RootPasswordDialog.py
netdriveconnector/RootPasswordDialog.ui
netdriveconnector/__init__.py
netdriveconnector/main.py
