Metadata-Version: 2.0
Name: netdrive-connector
Version: 1.3.2
Summary: GUI tool to setup mountable SFTP and WebDAV connections on Linux/UNIX systems.
Home-page: http://github.com/ethoms/netdrive-connector/
Author: Euan Thoms
Author-email: euan@potensol.com
License: BSD License
Keywords: connect remote network filesystem mount davfs webdav fuse sshfs sftp
Platform: UNKNOWN
Classifier: Environment :: X11 Applications :: Qt
Classifier: Intended Audience :: End Users/Desktop
Classifier: License :: OSI Approved :: BSD License
Classifier: Operating System :: POSIX :: Linux
Classifier: Programming Language :: Python
Classifier: Programming Language :: Python :: 2
Classifier: Programming Language :: Python :: 2.6
Classifier: Programming Language :: Python :: 2.7
Classifier: Topic :: Utilities
Classifier: Topic :: System :: Networking
Classifier: Topic :: System :: Systems Administration
